mdformat_space_control/__init__.py
mdformat_space_control/config.py
mdformat_space_control/plugin.py
mdformat_space_control-0.3.0.dist-info/entry_points.txt
mdformat_space_control-0.3.0.dist-info/licenses/LICENSE
mdformat_space_control-0.3.0.dist-info/WHEEL
mdformat_space_control-0.3.0.dist-info/METADATA
mdformat_space_control-0.3.0.dist-info/RECORD
