Metadata-Version: 2.4
Name: mdformat_space_control
Version: 0.3.0
Summary: An mdformat plugin for space control: EditorConfig indentation, tight lists, frontmatter spacing, and wikilinks.
Keywords: mdformat,markdown,formatter,editorconfig,indentation,lists,frontmatter,wikilink,obsidian
Author-email: Joseph Monaco <joe@selfmotion.net>
Requires-Python: >=3.10
Classifier: Development Status :: 3 - Alpha
Classifier: Intended Audience :: Developers
Classifier: License :: OSI Approved :: MIT License
Classifier: Programming Language :: Python :: 3
Classifier: Programming Language :: Python :: 3.10
Classifier: Programming Language :: Python :: 3.11
Classifier: Programming Language :: Python :: 3.12
Classifier: Programming Language :: Python :: 3.13
Classifier: Topic :: Software Development :: Libraries :: Python Modules
Classifier: Topic :: Text Processing :: Markup :: Markdown
License-File: LICENSE
Requires-Dist: mdformat>=0.7.0
Requires-Dist: editorconfig>=0.12.0
Requires-Dist: pytest>=7.0 ; extra == "test"
Requires-Dist: pytest-cov>=4.0 ; extra == "test"
Requires-Dist: mdformat-frontmatter>=2.0.0 ; extra == "test"
Requires-Dist: mdformat-simple-breaks>=0.1.0 ; extra == "test"
Project-URL: Homepage, https://github.com/jdmonaco/mdformat-space-control
Provides-Extra: test
